{"node":{"07154afeba559bb34278c1be0e7de0eb19796263":{"workers":{"app/_not-found/page":"2998","app/page":"2998","app/(auth)/register/page":"2998","app/(auth)/login/page":"2998","app/(admin)/dashboard/page":"2998"},"layer":{"app/_not-found/page":"rsc","app/page":"rsc","app/(auth)/register/page":"rsc","app/(auth)/login/page":"rsc","app/(admin)/dashboard/page":"rsc"}},"162593df8c4e83ec8d5aca39471c4823334e9e43":{"workers":{"app/_not-found/page":"2998","app/page":"2998","app/(auth)/register/page":"2998","app/(auth)/login/page":"2998","app/(admin)/dashboard/page":"2998"},"layer":{"app/_not-found/page":"rsc","app/page":"rsc","app/(auth)/register/page":"rsc","app/(auth)/login/page":"rsc","app/(admin)/dashboard/page":"rsc"}},"9d4293205af8fd1d8f753142d4257a11e881697d":{"workers":{"app/_not-found/page":"2998","app/page":"2998","app/(auth)/register/page":"2998","app/(auth)/login/page":"2998","app/(admin)/dashboard/page":"2998"},"layer":{"app/_not-found/page":"rsc","app/page":"rsc","app/(auth)/register/page":"rsc","app/(auth)/login/page":"rsc","app/(admin)/dashboard/page":"rsc"}},"e496534c60a406a67803e684de972d58b466e033":{"workers":{"app/_not-found/page":"2998","app/page":"2998","app/(auth)/register/page":"2998","app/(auth)/login/page":"2998","app/(admin)/dashboard/page":"2998"},"layer":{"app/_not-found/page":"rsc","app/page":"rsc","app/(auth)/register/page":"rsc","app/(auth)/login/page":"rsc","app/(admin)/dashboard/page":"rsc"}}},"edge":{},"encryptionKey":"hQBJ7cJLJDxpwMtIzXufxr+A9nhJl+LwL4Mm5df7a1A="}